{
  "type": "music",
  "id": "robocat",
  "bpm": 129,
  "ticksPerBeat": 96,
  "lengthTicks": 6239,
  "loop": {
    "enabled": false,
    "startTick": 0,
    "endTick": 6239
  },
  "instruments": [
    {
      "id": "lead",
      "wave": "triangle",
      "volume": 34,
      "attackMs": 8,
      "decayMs": 140
    },
    {
      "id": "bass",
      "wave": "triangle",
      "volume": 42,
      "attackMs": 10,
      "decayMs": 180
    },
    {
      "id": "harmony",
      "wave": "sine",
      "volume": 28,
      "attackMs": 16,
      "decayMs": 240
    },
    {
      "id": "soft_lead",
      "wave": "sine",
      "volume": 32,
      "attackMs": 10,
      "decayMs": 160
    },
    {
      "id": "spark",
      "wave": "triangle",
      "volume": 22,
      "attackMs": 6,
      "decayMs": 100
    },
    {
      "id": "lead_6",
      "wave": "triangle",
      "volume": 34,
      "attackMs": 8,
      "decayMs": 140
    },
    {
      "id": "bass_7",
      "wave": "triangle",
      "volume": 42,
      "attackMs": 10,
      "decayMs": 180
    },
    {
      "id": "harmony_8",
      "wave": "sine",
      "volume": 28,
      "attackMs": 16,
      "decayMs": 240
    }
  ],
  "notes": [
    {
      "instrument": 0,
      "note": 60,
      "startTick": 1,
      "durationTicks": 85,
      "volume": 60
    },
    {
      "instrument": 0,
      "note": 63,
      "startTick": 1,
      "durationTicks": 94,
      "volume": 60
    },
    {
      "instrument": 0,
      "note": 67,
      "startTick": 1,
      "durationTicks": 94,
      "volume": 60
    },
    {
      "instrument": 0,
      "note": 72,
      "startTick": 1,
      "durationTicks": 85,
      "volume": 60
    },
    {
      "instrument": 1,
      "note": 48,
      "startTick": 1,
      "durationTicks": 379,
      "volume": 47
    },
    {
      "instrument": 4,
      "note": 60,
      "startTick": 1,
      "durationTicks": 85,
      "volume": 50
    },
    {
      "instrument": 4,
      "note": 63,
      "startTick": 1,
      "durationTicks": 94,
      "volume": 50
    },
    {
      "instrument": 4,
      "note": 67,
      "startTick": 1,
      "durationTicks": 94,
      "volume": 50
    },
    {
      "instrument": 4,
      "note": 72,
      "startTick": 1,
      "durationTicks": 85,
      "volume": 50
    },
    {
      "instrument": 0,
      "note": 60,
      "startTick": 96,
      "durationTicks": 23,
      "volume": 60
    },
    {
      "instrument": 0,
      "note": 72,
      "startTick": 96,
      "durationTicks": 23,
      "volume": 60
    },
    {
      "instrument": 4,
      "note": 60,
      "startTick": 96,
      "durationTicks": 23,
      "volume": 50
    },
    {
      "instrument": 4,
      "note": 72,
      "startTick": 96,
      "durationTicks": 23,
      "volume": 50
    },
    {
      "instrument": 0,
      "note": 60,
      "startTick": 144,
      "durationTicks": 190,
      "volume": 60
    },
    {
      "instrument": 0,
      "note": 63,
      "startTick": 144,
      "durationTicks": 190,
      "volume": 60
    },
    {
      "instrument": 0,
      "note": 67,
      "startTick": 144,
      "durationTicks": 190,
      "volume": 60
    },
    {
      "instrument": 0,
      "note": 72,
      "startTick": 144,
      "durationTicks": 190,
      "volume": 60
    },
    {
      "instrument": 4,
      "note": 60,
      "startTick": 144,
      "durationTicks": 190,
      "volume": 50
    },
    {
      "instrument": 4,
      "note": 63,
      "startTick": 144,
      "durationTicks": 190,
      "volume": 50
    },
    {
      "instrument": 4,
      "note": 67,
      "startTick": 144,
      "durationTicks": 190,
      "volume": 50
    },
    {
      "instrument": 4,
      "note": 72,
      "startTick": 144,
      "durationTicks": 190,
      "volume": 50
    },
    {
      "instrument": 1,
      "note": 48,
      "startTick": 192,
      "durationTicks": 190,
      "volume": 47
    },
    {
      "instrument": 2,
      "note": 79,
      "startTick": 288,
      "durationTicks": 23,
      "volume": 56
    },
    {
      "instrument": 2,
      "note": 75,
      "startTick": 312,
      "durationTicks": 23,
      "volume": 56
    },
    {
      "instrument": 2,
      "note": 75,
      "startTick": 336,
      "durationTicks": 23,
      "volume": 56
    },
    {
      "instrument": 2,
      "note": 72,
      "startTick": 360,
      "durationTicks": 23,
      "volume": 56
    },
    {
      "instrument": 0,
      "note": 58,
      "startTick": 384,
      "durationTicks": 95,
      "volume": 60
    },
    {
      "instrument": 0,
      "note": 62,
      "startTick": 384,
      "durationTicks": 95,
      "volume": 60
    },
    {
      "instrument": 0,
      "note": 65,
      "startTick": 384,
      "durationTicks": 95,
      "volume": 60
    },
    {
      "instrument": 0,
      "note": 70,
      "startTick": 384,
      "durationTicks": 95,
      "volume": 60
    },
    {
      "instrument": 1,
      "note": 46,
      "startTick": 384,
      "durationTicks": 191,
      "volume": 47
    },
    {
      "instrument": 0,
      "note": 58,
      "startTick": 480,
      "durationTicks": 47,
      "volume": 60
    },
    {
      "instrument": 0,
      "note": 70,
      "startTick": 480,
      "durationTicks": 47,
      "volume": 60
    },
    {
      "instrument": 0,
      "note": 58,
      "startTick": 528,
      "durationTicks": 191,
      "volume": 60
    },
    {
      "instrument": 0,
      "note": 62,
      "startTick": 528,
      "durationTicks": 191,
      "volume": 60
    },
    {
      "instrument": 0,
      "note": 65,
      "startTick": 528,
      "durationTicks": 191,
      "volume": 60
    },
    {
      "instrument": 0,
      "note": 70,
      "startTick": 528,
      "durationTicks": 191,
      "volume": 60
    },
    {
      "instrument": 1,
      "note": 46,
      "startTick": 576,
      "durationTicks": 191,
      "volume": 47
    },
    {
      "instrument": 2,
      "note": 70,
      "startTick": 672,
      "durationTicks": 23,
      "volume": 56
    },
    {
      "instrument": 2,
      "note": 70,
      "startTick": 696,
      "durationTicks": 23,
      "volume": 56
    },
    {
      "instrument": 2,
      "note": 70,
      "startTick": 720,
      "durationTicks": 23,
      "volume": 56
    },
    {
      "instrument": 2,
      "note": 70,
      "startTick": 744,
      "durationTicks": 23,
      "volume": 56
    },
    {
      "instrument": 0,
      "note": 60,
      "startTick": 768,
      "durationTicks": 86,
      "volume": 60
    },
    {
      "instrument": 0,
      "note": 63,
      "startTick": 768,
      "durationTicks": 95,
      "volume": 60
    },
    {
      "instrument": 0,
      "note": 67,
      "startTick": 768,
      "durationTicks": 95,
      "volume": 60
    },
    {
      "instrument": 0,
      "note": 72,
      "startTick": 768,
      "durationTicks": 86,
      "volume": 60
    },
    {
      "instrument": 1,
      "note": 48,
      "startTick": 768,
      "durationTicks": 190,
      "volume": 47
    },
    {
      "instrument": 4,
      "note": 60,
      "startTick": 768,
      "durationTicks": 86,
      "volume": 50
    },
    {
      "instrument": 4,
      "note": 63,
      "startTick": 768,
      "durationTicks": 95,
      "volume": 50
    },
    {
      "instrument": 4,
      "note": 67,
      "startTick": 768,
      "durationTicks": 95,
      "volume": 50
    },
    {
      "instrument": 4,
      "note": 72,
      "startTick": 768,
      "durationTicks": 86,
      "volume": 50
    },
    {
      "instrument": 0,
      "note": 60,
      "startTick": 864,
      "durationTicks": 23,
      "volume": 60
    },
    {
      "instrument": 0,
      "note": 72,
      "startTick": 864,
      "durationTicks": 23,
      "volume": 60
    },
    {
      "instrument": 4,
      "note": 60,
      "startTick": 864,
      "durationTicks": 23,
      "volume": 50
    },
    {
      "instrument": 4,
      "note": 72,
      "startTick": 864,
      "durationTicks": 23,
      "volume": 50
    },
    {
      "instrument": 0,
      "note": 60,
      "startTick": 912,
      "durationTicks": 190,
      "volume": 60
    },
    {
      "instrument": 0,
      "note": 63,
      "startTick": 912,
      "durationTicks": 190,
      "volume": 60
    },
    {
      "instrument": 0,
      "note": 67,
      "startTick": 912,
      "durationTicks": 190,
      "volume": 60
    },
    {
      "instrument": 0,
      "note": 72,
      "startTick": 912,
      "durationTicks": 190,
      "volume": 60
    },
    {
      "instrument": 4,
      "note": 60,
      "startTick": 912,
      "durationTicks": 190,
      "volume": 50
    },
    {
      "instrument": 4,
      "note": 63,
      "startTick": 912,
      "durationTicks": 190,
      "volume": 50
    },
    {
      "instrument": 4,
      "note": 67,
      "startTick": 912,
      "durationTicks": 190,
      "volume": 50
    },
    {
      "instrument": 4,
      "note": 72,
      "startTick": 912,
      "durationTicks": 190,
      "volume": 50
    },
    {
      "instrument": 1,
      "note": 48,
      "startTick": 960,
      "durationTicks": 190,
      "volume": 47
    },
    {
      "instrument": 2,
      "note": 72,
      "startTick": 1008,
      "durationTicks": 47,
      "volume": 56
    },
    {
      "instrument": 2,
      "note": 72,
      "startTick": 1056,
      "durationTicks": 47,
      "volume": 56
    },
    {
      "instrument": 2,
      "note": 67,
      "startTick": 1104,
      "durationTicks": 47,
      "volume": 56
    },
    {
      "instrument": 0,
      "note": 60,
      "startTick": 1152,
      "durationTicks": 95,
      "volume": 60
    },
    {
      "instrument": 0,
      "note": 63,
      "startTick": 1152,
      "durationTicks": 95,
      "volume": 60
    },
    {
      "instrument": 0,
      "note": 68,
      "startTick": 1152,
      "durationTicks": 95,
      "volume": 60
    },
    {
      "instrument": 0,
      "note": 72,
      "startTick": 1152,
      "durationTicks": 95,
      "volume": 60
    },
    {
      "instrument": 1,
      "note": 44,
      "startTick": 1152,
      "durationTicks": 191,
      "volume": 47
    },
    {
      "instrument": 2,
      "note": 68,
      "startTick": 1152,
      "durationTicks": 47,
      "volume": 56
    },
    {
      "instrument": 0,
      "note": 60,
      "startTick": 1248,
      "durationTicks": 47,
      "volume": 60
    },
    {
      "instrument": 0,
      "note": 72,
      "startTick": 1248,
      "durationTicks": 47,
      "volume": 60
    },
    {
      "instrument": 0,
      "note": 60,
      "startTick": 1296,
      "durationTicks": 191,
      "volume": 60
    },
    {
      "instrument": 0,
      "note": 63,
      "startTick": 1296,
      "durationTicks": 191,
      "volume": 60
    },
    {
      "instrument": 0,
      "note": 68,
      "startTick": 1296,
      "durationTicks": 191,
      "volume": 60
    },
    {
      "instrument": 0,
      "note": 72,
      "startTick": 1296,
      "durationTicks": 191,
      "volume": 60
    },
    {
      "instrument": 1,
      "note": 44,
      "startTick": 1344,
      "durationTicks": 191,
      "volume": 47
    },
    {
      "instrument": 2,
      "note": 72,
      "startTick": 1344,
      "durationTicks": 47,
      "volume": 56
    },
    {
      "instrument": 2,
      "note": 65,
      "startTick": 1392,
      "durationTicks": 47,
      "volume": 56
    },
    {
      "instrument": 2,
      "note": 63,
      "startTick": 1440,
      "durationTicks": 47,
      "volume": 56
    },
    {
      "instrument": 2,
      "note": 62,
      "startTick": 1488,
      "durationTicks": 47,
      "volume": 56
    },
    {
      "instrument": 0,
      "note": 60,
      "startTick": 1536,
      "durationTicks": 86,
      "volume": 60
    },
    {
      "instrument": 0,
      "note": 63,
      "startTick": 1536,
      "durationTicks": 95,
      "volume": 60
    },
    {
      "instrument": 0,
      "note": 67,
      "startTick": 1536,
      "durationTicks": 95,
      "volume": 60
    },
    {
      "instrument": 0,
      "note": 72,
      "startTick": 1536,
      "durationTicks": 86,
      "volume": 60
    },
    {
      "instrument": 1,
      "note": 48,
      "startTick": 1536,
      "durationTicks": 380,
      "volume": 47
    },
    {
      "instrument": 4,
      "note": 60,
      "startTick": 1536,
      "durationTicks": 86,
      "volume": 50
    },
    {
      "instrument": 4,
      "note": 63,
      "startTick": 1536,
      "durationTicks": 95,
      "volume": 50
    },
    {
      "instrument": 4,
      "note": 67,
      "startTick": 1536,
      "durationTicks": 95,
      "volume": 50
    },
    {
      "instrument": 4,
      "note": 72,
      "startTick": 1536,
      "durationTicks": 86,
      "volume": 50
    },
    {
      "instrument": 0,
      "note": 60,
      "startTick": 1632,
      "durationTicks": 23,
      "volume": 60
    },
    {
      "instrument": 0,
      "note": 72,
      "startTick": 1632,
      "durationTicks": 23,
      "volume": 60
    },
    {
      "instrument": 2,
      "note": 79,
      "startTick": 1632,
      "durationTicks": 23,
      "volume": 56
    },
    {
      "instrument": 4,
      "note": 60,
      "startTick": 1632,
      "durationTicks": 23,
      "volume": 50
    },
    {
      "instrument": 4,
      "note": 72,
      "startTick": 1632,
      "durationTicks": 23,
      "volume": 50
    },
    {
      "instrument": 2,
      "note": 79,
      "startTick": 1656,
      "durationTicks": 23,
      "volume": 56
    },
    {
      "instrument": 0,
      "note": 60,
      "startTick": 1680,
      "durationTicks": 190,
      "volume": 60
    },
    {
      "instrument": 0,
      "note": 63,
      "startTick": 1680,
      "durationTicks": 190,
      "volume": 60
    },
    {
      "instrument": 0,
      "note": 67,
      "startTick": 1680,
      "durationTicks": 190,
      "volume": 60
    },
    {
      "instrument": 0,
      "note": 72,
      "startTick": 1680,
      "durationTicks": 190,
      "volume": 60
    },
    {
      "instrument": 2,
      "note": 79,
      "startTick": 1680,
      "durationTicks": 23,
      "volume": 56
    },
    {
      "instrument": 4,
      "note": 60,
      "startTick": 1680,
      "durationTicks": 190,
      "volume": 50
    },
    {
      "instrument": 4,
      "note": 63,
      "startTick": 1680,
      "durationTicks": 190,
      "volume": 50
    },
    {
      "instrument": 4,
      "note": 67,
      "startTick": 1680,
      "durationTicks": 190,
      "volume": 50
    },
    {
      "instrument": 4,
      "note": 72,
      "startTick": 1680,
      "durationTicks": 190,
      "volume": 50
    },
    {
      "instrument": 2,
      "note": 79,
      "startTick": 1704,
      "durationTicks": 23,
      "volume": 56
    },
    {
      "instrument": 1,
      "note": 48,
      "startTick": 1728,
      "durationTicks": 190,
      "volume": 47
    },
    {
      "instrument": 2,
      "note": 75,
      "startTick": 1728,
      "durationTicks": 23,
      "volume": 56
    },
    {
      "instrument": 2,
      "note": 75,
      "startTick": 1752,
      "durationTicks": 23,
      "volume": 56
    },
    {
      "instrument": 2,
      "note": 75,
      "startTick": 1776,
      "durationTicks": 23,
      "volume": 56
    },
    {
      "instrument": 2,
      "note": 75,
      "startTick": 1800,
      "durationTicks": 23,
      "volume": 56
    },
    {
      "instrument": 2,
      "note": 72,
      "startTick": 1824,
      "durationTicks": 23,
      "volume": 56
    },
    {
      "instrument": 2,
      "note": 72,
      "startTick": 1872,
      "durationTicks": 23,
      "volume": 56
    },
    {
      "instrument": 0,
      "note": 58,
      "startTick": 1920,
      "durationTicks": 95,
      "volume": 60
    },
    {
      "instrument": 0,
      "note": 62,
      "startTick": 1920,
      "durationTicks": 95,
      "volume": 60
    },
    {
      "instrument": 0,
      "note": 65,
      "startTick": 1920,
      "durationTicks": 95,
      "volume": 60
    },
    {
      "instrument": 0,
      "note": 70,
      "startTick": 1920,
      "durationTicks": 95,
      "volume": 60
    },
    {
      "instrument": 1,
      "note": 46,
      "startTick": 1920,
      "durationTicks": 191,
      "volume": 47
    },
    {
      "instrument": 0,
      "note": 58,
      "startTick": 2016,
      "durationTicks": 47,
      "volume": 60
    },
    {
      "instrument": 0,
      "note": 70,
      "startTick": 2016,
      "durationTicks": 47,
      "volume": 60
    },
    {
      "instrument": 2,
      "note": 77,
      "startTick": 2016,
      "durationTicks": 23,
      "volume": 56
    },
    {
      "instrument": 2,
      "note": 77,
      "startTick": 2040,
      "durationTicks": 23,
      "volume": 56
    },
    {
      "instrument": 0,
      "note": 58,
      "startTick": 2064,
      "durationTicks": 191,
      "volume": 60
    },
    {
      "instrument": 0,
      "note": 62,
      "startTick": 2064,
      "durationTicks": 191,
      "volume": 60
    },
    {
      "instrument": 0,
      "note": 65,
      "startTick": 2064,
      "durationTicks": 191,
      "volume": 60
    },
    {
      "instrument": 0,
      "note": 70,
      "startTick": 2064,
      "durationTicks": 191,
      "volume": 60
    },
    {
      "instrument": 2,
      "note": 77,
      "startTick": 2064,
      "durationTicks": 23,
      "volume": 56
    },
    {
      "instrument": 2,
      "note": 77,
      "startTick": 2088,
      "durationTicks": 23,
      "volume": 56
    },
    {
      "instrument": 1,
      "note": 46,
      "startTick": 2112,
      "durationTicks": 191,
      "volume": 47
    },
    {
      "instrument": 2,
      "note": 74,
      "startTick": 2112,
      "durationTicks": 23,
      "volume": 56
    },
    {
      "instrument": 2,
      "note": 74,
      "startTick": 2136,
      "durationTicks": 23,
      "volume": 56
    },
    {
      "instrument": 2,
      "note": 74,
      "startTick": 2160,
      "durationTicks": 23,
      "volume": 56
    },
    {
      "instrument": 2,
      "note": 74,
      "startTick": 2184,
      "durationTicks": 23,
      "volume": 56
    },
    {
      "instrument": 2,
      "note": 70,
      "startTick": 2208,
      "durationTicks": 23,
      "volume": 56
    },
    {
      "instrument": 2,
      "note": 70,
      "startTick": 2256,
      "durationTicks": 23,
      "volume": 56
    },
    {
      "instrument": 0,
      "note": 58,
      "startTick": 2304,
      "durationTicks": 95,
      "volume": 60
    },
    {
      "instrument": 0,
      "note": 62,
      "startTick": 2304,
      "durationTicks": 95,
      "volume": 60
    },
    {
      "instrument": 0,
      "note": 67,
      "startTick": 2304,
      "durationTicks": 95,
      "volume": 60
    },
    {
      "instrument": 0,
      "note": 70,
      "startTick": 2304,
      "durationTicks": 95,
      "volume": 60
    },
    {
      "instrument": 1,
      "note": 55,
      "startTick": 2304,
      "durationTicks": 191,
      "volume": 47
    },
    {
      "instrument": 0,
      "note": 58,
      "startTick": 2400,
      "durationTicks": 47,
      "volume": 60
    },
    {
      "instrument": 0,
      "note": 70,
      "startTick": 2400,
      "durationTicks": 47,
      "volume": 60
    },
    {
      "instrument": 1,
      "note": 50,
      "startTick": 2400,
      "durationTicks": 95,
      "volume": 47
    },
    {
      "instrument": 0,
      "note": 58,
      "startTick": 2448,
      "durationTicks": 191,
      "volume": 60
    },
    {
      "instrument": 0,
      "note": 62,
      "startTick": 2448,
      "durationTicks": 191,
      "volume": 60
    },
    {
      "instrument": 0,
      "note": 67,
      "startTick": 2448,
      "durationTicks": 191,
      "volume": 60
    },
    {
      "instrument": 0,
      "note": 70,
      "startTick": 2448,
      "durationTicks": 191,
      "volume": 60
    },
    {
      "instrument": 1,
      "note": 43,
      "startTick": 2544,
      "durationTicks": 47,
      "volume": 47
    },
    {
      "instrument": 1,
      "note": 55,
      "startTick": 2544,
      "durationTicks": 47,
      "volume": 47
    },
    {
      "instrument": 1,
      "note": 43,
      "startTick": 2592,
      "durationTicks": 47,
      "volume": 47
    },
    {
      "instrument": 1,
      "note": 55,
      "startTick": 2592,
      "durationTicks": 47,
      "volume": 47
    },
    {
      "instrument": 1,
      "note": 41,
      "startTick": 2640,
      "durationTicks": 47,
      "volume": 47
    },
    {
      "instrument": 1,
      "note": 53,
      "startTick": 2640,
      "durationTicks": 47,
      "volume": 47
    },
    {
      "instrument": 0,
      "note": 58,
      "startTick": 2688,
      "durationTicks": 23,
      "volume": 60
    },
    {
      "instrument": 0,
      "note": 62,
      "startTick": 2688,
      "durationTicks": 23,
      "volume": 60
    },
    {
      "instrument": 0,
      "note": 67,
      "startTick": 2688,
      "durationTicks": 23,
      "volume": 60
    },
    {
      "instrument": 0,
      "note": 70,
      "startTick": 2688,
      "durationTicks": 23,
      "volume": 60
    },
    {
      "instrument": 1,
      "note": 55,
      "startTick": 2688,
      "durationTicks": 47,
      "volume": 47
    },
    {
      "instrument": 0,
      "note": 58,
      "startTick": 2736,
      "durationTicks": 23,
      "volume": 60
    },
    {
      "instrument": 0,
      "note": 62,
      "startTick": 2736,
      "durationTicks": 23,
      "volume": 60
    },
    {
      "instrument": 0,
      "note": 67,
      "startTick": 2736,
      "durationTicks": 23,
      "volume": 60
    },
    {
      "instrument": 0,
      "note": 70,
      "startTick": 2736,
      "durationTicks": 23,
      "volume": 60
    },
    {
      "instrument": 2,
      "note": 57,
      "startTick": 2736,
      "durationTicks": 23,
      "volume": 56
    },
    {
      "instrument": 2,
      "note": 59,
      "startTick": 2760,
      "durationTicks": 23,
      "volume": 56
    },
    {
      "instrument": 0,
      "note": 58,
      "startTick": 2784,
      "durationTicks": 23,
      "volume": 60
    },
    {
      "instrument": 0,
      "note": 62,
      "startTick": 2784,
      "durationTicks": 23,
      "volume": 60
    },
    {
      "instrument": 0,
      "note": 67,
      "startTick": 2784,
      "durationTicks": 23,
      "volume": 60
    },
    {
      "instrument": 0,
      "note": 70,
      "startTick": 2784,
      "durationTicks": 23,
      "volume": 60
    },
    {
      "instrument": 1,
      "note": 50,
      "startTick": 2784,
      "durationTicks": 47,
      "volume": 47
    },
    {
      "instrument": 2,
      "note": 62,
      "startTick": 2784,
      "durationTicks": 23,
      "volume": 56
    },
    {
      "instrument": 2,
      "note": 64,
      "startTick": 2808,
      "durationTicks": 23,
      "volume": 56
    },
    {
      "instrument": 0,
      "note": 58,
      "startTick": 2832,
      "durationTicks": 191,
      "volume": 60
    },
    {
      "instrument": 0,
      "note": 62,
      "startTick": 2832,
      "durationTicks": 191,
      "volume": 60
    },
    {
      "instrument": 0,
      "note": 67,
      "startTick": 2832,
      "durationTicks": 191,
      "volume": 60
    },
    {
      "instrument": 0,
      "note": 70,
      "startTick": 2832,
      "durationTicks": 191,
      "volume": 60
    },
    {
      "instrument": 2,
      "note": 65,
      "startTick": 2832,
      "durationTicks": 23,
      "volume": 56
    },
    {
      "instrument": 2,
      "note": 67,
      "startTick": 2856,
      "durationTicks": 23,
      "volume": 56
    },
    {
      "instrument": 1,
      "note": 43,
      "startTick": 2880,
      "durationTicks": 95,
      "volume": 47
    },
    {
      "instrument": 1,
      "note": 55,
      "startTick": 2880,
      "durationTicks": 95,
      "volume": 47
    },
    {
      "instrument": 2,
      "note": 69,
      "startTick": 2880,
      "durationTicks": 23,
      "volume": 56
    },
    {
      "instrument": 2,
      "note": 71,
      "startTick": 2904,
      "durationTicks": 23,
      "volume": 56
    },
    {
      "instrument": 1,
      "note": 41,
      "startTick": 2928,
      "durationTicks": 95,
      "volume": 47
    },
    {
      "instrument": 1,
      "note": 53,
      "startTick": 2928,
      "durationTicks": 95,
      "volume": 47
    },
    {
      "instrument": 2,
      "note": 72,
      "startTick": 2928,
      "durationTicks": 23,
      "volume": 56
    },
    {
      "instrument": 2,
      "note": 74,
      "startTick": 2952,
      "durationTicks": 23,
      "volume": 56
    },
    {
      "instrument": 1,
      "note": 39,
      "startTick": 2976,
      "durationTicks": 95,
      "volume": 47
    },
    {
      "instrument": 1,
      "note": 51,
      "startTick": 2976,
      "durationTicks": 95,
      "volume": 47
    },
    {
      "instrument": 1,
      "note": 63,
      "startTick": 2976,
      "durationTicks": 47,
      "volume": 47
    },
    {
      "instrument": 2,
      "note": 76,
      "startTick": 2976,
      "durationTicks": 23,
      "volume": 56
    },
    {
      "instrument": 2,
      "note": 76,
      "startTick": 3000,
      "durationTicks": 23,
      "volume": 56
    },
    {
      "instrument": 1,
      "note": 38,
      "startTick": 3024,
      "durationTicks": 47,
      "volume": 47
    },
    {
      "instrument": 1,
      "note": 50,
      "startTick": 3024,
      "durationTicks": 47,
      "volume": 47
    },
    {
      "instrument": 1,
      "note": 62,
      "startTick": 3024,
      "durationTicks": 47,
      "volume": 47
    },
    {
      "instrument": 2,
      "note": 75,
      "startTick": 3024,
      "durationTicks": 23,
      "volume": 56
    },
    {
      "instrument": 2,
      "note": 74,
      "startTick": 3048,
      "durationTicks": 23,
      "volume": 56
    },
    {
      "instrument": 1,
      "note": 60,
      "startTick": 3072,
      "durationTicks": 95,
      "volume": 47
    },
    {
      "instrument": 2,
      "note": 72,
      "startTick": 3072,
      "durationTicks": 23,
      "volume": 56
    },
    {
      "instrument": 2,
      "note": 79,
      "startTick": 3072,
      "durationTicks": 23,
      "volume": 72
    },
    {
      "instrument": 4,
      "note": 48,
      "startTick": 3072,
      "durationTicks": 191,
      "volume": 45
    },
    {
      "instrument": 2,
      "note": 77,
      "startTick": 3096,
      "durationTicks": 23,
      "volume": 72
    },
    {
      "instrument": 2,
      "note": 75,
      "startTick": 3120,
      "durationTicks": 47,
      "volume": 72
    },
    {
      "instrument": 3,
      "note": 60,
      "startTick": 3120,
      "durationTicks": 47,
      "volume": 70
    },
    {
      "instrument": 3,
      "note": 72,
      "startTick": 3120,
      "durationTicks": 47,
      "volume": 70
    },
    {
      "instrument": 3,
      "note": 84,
      "startTick": 3120,
      "durationTicks": 95,
      "volume": 70
    },
    {
      "instrument": 5,
      "note": 60,
      "startTick": 3120,
      "durationTicks": 47,
      "volume": 72
    },
    {
      "instrument": 5,
      "note": 72,
      "startTick": 3120,
      "durationTicks": 47,
      "volume": 72
    },
    {
      "instrument": 5,
      "note": 84,
      "startTick": 3120,
      "durationTicks": 95,
      "volume": 72
    },
    {
      "instrument": 1,
      "note": 55,
      "startTick": 3168,
      "durationTicks": 95,
      "volume": 47
    },
    {
      "instrument": 3,
      "note": 63,
      "startTick": 3168,
      "durationTicks": 47,
      "volume": 70
    },
    {
      "instrument": 3,
      "note": 75,
      "startTick": 3168,
      "durationTicks": 47,
      "volume": 70
    },
    {
      "instrument": 4,
      "note": 43,
      "startTick": 3168,
      "durationTicks": 95,
      "volume": 45
    },
    {
      "instrument": 5,
      "note": 63,
      "startTick": 3168,
      "durationTicks": 47,
      "volume": 72
    },
    {
      "instrument": 5,
      "note": 75,
      "startTick": 3168,
      "durationTicks": 47,
      "volume": 72
    },
    {
      "instrument": 3,
      "note": 60,
      "startTick": 3216,
      "durationTicks": 47,
      "volume": 70
    },
    {
      "instrument": 3,
      "note": 72,
      "startTick": 3216,
      "durationTicks": 47,
      "volume": 70
    },
    {
      "instrument": 5,
      "note": 60,
      "startTick": 3216,
      "durationTicks": 47,
      "volume": 72
    },
    {
      "instrument": 5,
      "note": 72,
      "startTick": 3216,
      "durationTicks": 47,
      "volume": 72
    },
    {
      "instrument": 1,
      "note": 58,
      "startTick": 3264,
      "durationTicks": 95,
      "volume": 47
    },
    {
      "instrument": 3,
      "note": 62,
      "startTick": 3264,
      "durationTicks": 95,
      "volume": 70
    },
    {
      "instrument": 3,
      "note": 74,
      "startTick": 3264,
      "durationTicks": 95,
      "volume": 70
    },
    {
      "instrument": 4,
      "note": 46,
      "startTick": 3264,
      "durationTicks": 95,
      "volume": 45
    },
    {
      "instrument": 5,
      "note": 62,
      "startTick": 3264,
      "durationTicks": 95,
      "volume": 72
    },
    {
      "instrument": 5,
      "note": 74,
      "startTick": 3264,
      "durationTicks": 95,
      "volume": 72
    },
    {
      "instrument": 1,
      "note": 55,
      "startTick": 3360,
      "durationTicks": 95,
      "volume": 47
    },
    {
      "instrument": 3,
      "note": 65,
      "startTick": 3360,
      "durationTicks": 95,
      "volume": 70
    },
    {
      "instrument": 3,
      "note": 77,
      "startTick": 3360,
      "durationTicks": 95,
      "volume": 70
    },
    {
      "instrument": 4,
      "note": 43,
      "startTick": 3360,
      "durationTicks": 95,
      "volume": 45
    },
    {
      "instrument": 5,
      "note": 65,
      "startTick": 3360,
      "durationTicks": 95,
      "volume": 72
    },
    {
      "instrument": 5,
      "note": 77,
      "startTick": 3360,
      "durationTicks": 95,
      "volume": 72
    },
    {
      "instrument": 1,
      "note": 60,
      "startTick": 3456,
      "durationTicks": 95,
      "volume": 47
    },
    {
      "instrument": 2,
      "note": 79,
      "startTick": 3456,
      "durationTicks": 23,
      "volume": 72
    },
    {
      "instrument": 4,
      "note": 48,
      "startTick": 3456,
      "durationTicks": 95,
      "volume": 45
    },
    {
      "instrument": 2,
      "note": 77,
      "startTick": 3480,
      "durationTicks": 23,
      "volume": 72
    },
    {
      "instrument": 2,
      "note": 75,
      "startTick": 3504,
      "durationTicks": 47,
      "volume": 72
    },
    {
      "instrument": 3,
      "note": 60,
      "startTick": 3504,
      "durationTicks": 47,
      "volume": 70
    },
    {
      "instrument": 3,
      "note": 72,
      "startTick": 3504,
      "durationTicks": 47,
      "volume": 70
    },
    {
      "instrument": 3,
      "note": 84,
      "startTick": 3504,
      "durationTicks": 47,
      "volume": 70
    },
    {
      "instrument": 5,
      "note": 60,
      "startTick": 3504,
      "durationTicks": 47,
      "volume": 72
    },
    {
      "instrument": 5,
      "note": 72,
      "startTick": 3504,
      "durationTicks": 47,
      "volume": 72
    },
    {
      "instrument": 5,
      "note": 84,
      "startTick": 3504,
      "durationTicks": 47,
      "volume": 72
    },
    {
      "instrument": 1,
      "note": 55,
      "startTick": 3552,
      "durationTicks": 95,
      "volume": 47
    },
    {
      "instrument": 3,
      "note": 63,
      "startTick": 3552,
      "durationTicks": 47,
      "volume": 70
    },
    {
      "instrument": 3,
      "note": 75,
      "startTick": 3552,
      "durationTicks": 47,
      "volume": 70
    },
    {
      "instrument": 4,
      "note": 43,
      "startTick": 3552,
      "durationTicks": 95,
      "volume": 45
    },
    {
      "instrument": 5,
      "note": 63,
      "startTick": 3552,
      "durationTicks": 47,
      "volume": 72
    },
    {
      "instrument": 5,
      "note": 75,
      "startTick": 3552,
      "durationTicks": 47,
      "volume": 72
    },
    {
      "instrument": 3,
      "note": 60,
      "startTick": 3600,
      "durationTicks": 47,
      "volume": 70
    },
    {
      "instrument": 3,
      "note": 72,
      "startTick": 3600,
      "durationTicks": 47,
      "volume": 70
    },
    {
      "instrument": 3,
      "note": 84,
      "startTick": 3600,
      "durationTicks": 47,
      "volume": 70
    },
    {
      "instrument": 5,
      "note": 60,
      "startTick": 3600,
      "durationTicks": 47,
      "volume": 72
    },
    {
      "instrument": 5,
      "note": 72,
      "startTick": 3600,
      "durationTicks": 47,
      "volume": 72
    },
    {
      "instrument": 5,
      "note": 84,
      "startTick": 3600,
      "durationTicks": 47,
      "volume": 72
    },
    {
      "instrument": 1,
      "note": 56,
      "startTick": 3648,
      "durationTicks": 95,
      "volume": 47
    },
    {
      "instrument": 3,
      "note": 56,
      "startTick": 3648,
      "durationTicks": 191,
      "volume": 70
    },
    {
      "instrument": 3,
      "note": 68,
      "startTick": 3648,
      "durationTicks": 191,
      "volume": 70
    },
    {
      "instrument": 4,
      "note": 55,
      "startTick": 3648,
      "durationTicks": 47,
      "volume": 45
    },
    {
      "instrument": 5,
      "note": 56,
      "startTick": 3648,
      "durationTicks": 191,
      "volume": 72
    },
    {
      "instrument": 5,
      "note": 68,
      "startTick": 3648,
      "durationTicks": 191,
      "volume": 72
    },
    {
      "instrument": 4,
      "note": 51,
      "startTick": 3696,
      "durationTicks": 47,
      "volume": 45
    },
    {
      "instrument": 1,
      "note": 55,
      "startTick": 3744,
      "durationTicks": 95,
      "volume": 47
    },
    {
      "instrument": 4,
      "note": 48,
      "startTick": 3744,
      "durationTicks": 47,
      "volume": 45
    },
    {
      "instrument": 4,
      "note": 43,
      "startTick": 3792,
      "durationTicks": 47,
      "volume": 45
    },
    {
      "instrument": 0,
      "note": 60,
      "startTick": 3840,
      "durationTicks": 172,
      "volume": 72
    },
    {
      "instrument": 1,
      "note": 60,
      "startTick": 3840,
      "durationTicks": 95,
      "volume": 47
    },
    {
      "instrument": 2,
      "note": 79,
      "startTick": 3840,
      "durationTicks": 23,
      "volume": 72
    },
    {
      "instrument": 4,
      "note": 48,
      "startTick": 3840,
      "durationTicks": 95,
      "volume": 45
    },
    {
      "instrument": 2,
      "note": 77,
      "startTick": 3864,
      "durationTicks": 23,
      "volume": 72
    },
    {
      "instrument": 2,
      "note": 75,
      "startTick": 3888,
      "durationTicks": 47,
      "volume": 72
    },
    {
      "instrument": 3,
      "note": 60,
      "startTick": 3888,
      "durationTicks": 47,
      "volume": 70
    },
    {
      "instrument": 3,
      "note": 72,
      "startTick": 3888,
      "durationTicks": 47,
      "volume": 70
    },
    {
      "instrument": 3,
      "note": 84,
      "startTick": 3888,
      "durationTicks": 95,
      "volume": 70
    },
    {
      "instrument": 5,
      "note": 60,
      "startTick": 3888,
      "durationTicks": 47,
      "volume": 72
    },
    {
      "instrument": 5,
      "note": 72,
      "startTick": 3888,
      "durationTicks": 47,
      "volume": 72
    },
    {
      "instrument": 5,
      "note": 84,
      "startTick": 3888,
      "durationTicks": 95,
      "volume": 72
    },
    {
      "instrument": 1,
      "note": 55,
      "startTick": 3936,
      "durationTicks": 95,
      "volume": 47
    },
    {
      "instrument": 3,
      "note": 63,
      "startTick": 3936,
      "durationTicks": 47,
      "volume": 70
    },
    {
      "instrument": 3,
      "note": 75,
      "startTick": 3936,
      "durationTicks": 47,
      "volume": 70
    },
    {
      "instrument": 4,
      "note": 43,
      "startTick": 3936,
      "durationTicks": 95,
      "volume": 45
    },
    {
      "instrument": 5,
      "note": 63,
      "startTick": 3936,
      "durationTicks": 47,
      "volume": 72
    },
    {
      "instrument": 5,
      "note": 75,
      "startTick": 3936,
      "durationTicks": 47,
      "volume": 72
    },
    {
      "instrument": 3,
      "note": 60,
      "startTick": 3984,
      "durationTicks": 47,
      "volume": 70
    },
    {
      "instrument": 3,
      "note": 72,
      "startTick": 3984,
      "durationTicks": 47,
      "volume": 70
    },
    {
      "instrument": 5,
      "note": 60,
      "startTick": 3984,
      "durationTicks": 47,
      "volume": 72
    },
    {
      "instrument": 5,
      "note": 72,
      "startTick": 3984,
      "durationTicks": 47,
      "volume": 72
    },
    {
      "instrument": 0,
      "note": 58,
      "startTick": 4032,
      "durationTicks": 172,
      "volume": 72
    },
    {
      "instrument": 1,
      "note": 58,
      "startTick": 4032,
      "durationTicks": 95,
      "volume": 47
    },
    {
      "instrument": 3,
      "note": 62,
      "startTick": 4032,
      "durationTicks": 95,
      "volume": 70
    },
    {
      "instrument": 3,
      "note": 74,
      "startTick": 4032,
      "durationTicks": 95,
      "volume": 70
    },
    {
      "instrument": 4,
      "note": 46,
      "startTick": 4032,
      "durationTicks": 95,
      "volume": 45
    },
    {
      "instrument": 5,
      "note": 62,
      "startTick": 4032,
      "durationTicks": 95,
      "volume": 72
    },
    {
      "instrument": 5,
      "note": 74,
      "startTick": 4032,
      "durationTicks": 95,
      "volume": 72
    },
    {
      "instrument": 1,
      "note": 58,
      "startTick": 4128,
      "durationTicks": 95,
      "volume": 47
    },
    {
      "instrument": 3,
      "note": 65,
      "startTick": 4128,
      "durationTicks": 95,
      "volume": 70
    },
    {
      "instrument": 3,
      "note": 77,
      "startTick": 4128,
      "durationTicks": 95,
      "volume": 70
    },
    {
      "instrument": 4,
      "note": 41,
      "startTick": 4128,
      "durationTicks": 95,
      "volume": 45
    },
    {
      "instrument": 5,
      "note": 65,
      "startTick": 4128,
      "durationTicks": 95,
      "volume": 72
    },
    {
      "instrument": 5,
      "note": 77,
      "startTick": 4128,
      "durationTicks": 95,
      "volume": 72
    },
    {
      "instrument": 0,
      "note": 67,
      "startTick": 4224,
      "durationTicks": 172,
      "volume": 72
    },
    {
      "instrument": 0,
      "note": 70,
      "startTick": 4224,
      "durationTicks": 172,
      "volume": 72
    },
    {
      "instrument": 0,
      "note": 74,
      "startTick": 4224,
      "durationTicks": 172,
      "volume": 72
    },
    {
      "instrument": 0,
      "note": 79,
      "startTick": 4224,
      "durationTicks": 172,
      "volume": 72
    },
    {
      "instrument": 0,
      "note": 82,
      "startTick": 4224,
      "durationTicks": 172,
      "volume": 72
    },
    {
      "instrument": 1,
      "note": 55,
      "startTick": 4224,
      "durationTicks": 86,
      "volume": 64
    },
    {
      "instrument": 3,
      "note": 58,
      "startTick": 4224,
      "durationTicks": 191,
      "volume": 70
    },
    {
      "instrument": 3,
      "note": 70,
      "startTick": 4224,
      "durationTicks": 191,
      "volume": 70
    },
    {
      "instrument": 4,
      "note": 43,
      "startTick": 4224,
      "durationTicks": 95,
      "volume": 45
    },
    {
      "instrument": 5,
      "note": 58,
      "startTick": 4224,
      "durationTicks": 191,
      "volume": 72
    },
    {
      "instrument": 5,
      "note": 70,
      "startTick": 4224,
      "durationTicks": 191,
      "volume": 72
    },
    {
      "instrument": 1,
      "note": 50,
      "startTick": 4320,
      "durationTicks": 86,
      "volume": 64
    },
    {
      "instrument": 4,
      "note": 43,
      "startTick": 4320,
      "durationTicks": 235,
      "volume": 62
    },
    {
      "instrument": 4,
      "note": 55,
      "startTick": 4320,
      "durationTicks": 235,
      "volume": 62
    },
    {
      "instrument": 0,
      "note": 67,
      "startTick": 4416,
      "durationTicks": 172,
      "volume": 72
    },
    {
      "instrument": 0,
      "note": 71,
      "startTick": 4416,
      "durationTicks": 172,
      "volume": 72
    },
    {
      "instrument": 0,
      "note": 74,
      "startTick": 4416,
      "durationTicks": 172,
      "volume": 72
    },
    {
      "instrument": 0,
      "note": 79,
      "startTick": 4416,
      "durationTicks": 172,
      "volume": 72
    },
    {
      "instrument": 0,
      "note": 83,
      "startTick": 4416,
      "durationTicks": 172,
      "volume": 72
    },
    {
      "instrument": 1,
      "note": 55,
      "startTick": 4416,
      "durationTicks": 86,
      "volume": 64
    },
    {
      "instrument": 1,
      "note": 53,
      "startTick": 4464,
      "durationTicks": 43,
      "volume": 64
    },
    {
      "instrument": 1,
      "note": 51,
      "startTick": 4512,
      "durationTicks": 43,
      "volume": 64
    },
    {
      "instrument": 4,
      "note": 43,
      "startTick": 4512,
      "durationTicks": 67,
      "volume": 62
    },
    {
      "instrument": 4,
      "note": 55,
      "startTick": 4512,
      "durationTicks": 67,
      "volume": 62
    },
    {
      "instrument": 1,
      "note": 50,
      "startTick": 4560,
      "durationTicks": 43,
      "volume": 64
    },
    {
      "instrument": 1,
      "note": 62,
      "startTick": 4560,
      "durationTicks": 43,
      "volume": 64
    },
    {
      "instrument": 0,
      "note": 63,
      "startTick": 4608,
      "durationTicks": 43,
      "volume": 72
    },
    {
      "instrument": 0,
      "note": 67,
      "startTick": 4608,
      "durationTicks": 43,
      "volume": 72
    },
    {
      "instrument": 0,
      "note": 72,
      "startTick": 4608,
      "durationTicks": 43,
      "volume": 72
    },
    {
      "instrument": 0,
      "note": 84,
      "startTick": 4608,
      "durationTicks": 43,
      "volume": 72
    },
    {
      "instrument": 0,
      "note": 87,
      "startTick": 4608,
      "durationTicks": 43,
      "volume": 72
    },
    {
      "instrument": 1,
      "note": 48,
      "startTick": 4608,
      "durationTicks": 43,
      "volume": 64
    },
    {
      "instrument": 1,
      "note": 60,
      "startTick": 4608,
      "durationTicks": 43,
      "volume": 64
    },
    {
      "instrument": 1,
      "note": 60,
      "startTick": 4608,
      "durationTicks": 95,
      "volume": 47
    },
    {
      "instrument": 2,
      "note": 79,
      "startTick": 4608,
      "durationTicks": 23,
      "volume": 72
    },
    {
      "instrument": 4,
      "note": 36,
      "startTick": 4608,
      "durationTicks": 172,
      "volume": 62
    },
    {
      "instrument": 4,
      "note": 48,
      "startTick": 4608,
      "durationTicks": 172,
      "volume": 62
    },
    {
      "instrument": 4,
      "note": 60,
      "startTick": 4608,
      "durationTicks": 172,
      "volume": 62
    },
    {
      "instrument": 2,
      "note": 77,
      "startTick": 4632,
      "durationTicks": 23,
      "volume": 72
    },
    {
      "instrument": 2,
      "note": 75,
      "startTick": 4656,
      "durationTicks": 47,
      "volume": 72
    },
    {
      "instrument": 3,
      "note": 60,
      "startTick": 4656,
      "durationTicks": 47,
      "volume": 70
    },
    {
      "instrument": 3,
      "note": 72,
      "startTick": 4656,
      "durationTicks": 47,
      "volume": 70
    },
    {
      "instrument": 3,
      "note": 84,
      "startTick": 4656,
      "durationTicks": 95,
      "volume": 70
    },
    {
      "instrument": 5,
      "note": 60,
      "startTick": 4656,
      "durationTicks": 47,
      "volume": 72
    },
    {
      "instrument": 5,
      "note": 72,
      "startTick": 4656,
      "durationTicks": 47,
      "volume": 72
    },
    {
      "instrument": 5,
      "note": 84,
      "startTick": 4656,
      "durationTicks": 95,
      "volume": 72
    },
    {
      "instrument": 1,
      "note": 43,
      "startTick": 4704,
      "durationTicks": 86,
      "volume": 64
    },
    {
      "instrument": 1,
      "note": 55,
      "startTick": 4704,
      "durationTicks": 95,
      "volume": 47
    },
    {
      "instrument": 3,
      "note": 63,
      "startTick": 4704,
      "durationTicks": 47,
      "volume": 70
    },
    {
      "instrument": 3,
      "note": 75,
      "startTick": 4704,
      "durationTicks": 47,
      "volume": 70
    },
    {
      "instrument": 5,
      "note": 63,
      "startTick": 4704,
      "durationTicks": 47,
      "volume": 72
    },
    {
      "instrument": 5,
      "note": 75,
      "startTick": 4704,
      "durationTicks": 47,
      "volume": 72
    },
    {
      "instrument": 3,
      "note": 60,
      "startTick": 4752,
      "durationTicks": 47,
      "volume": 70
    },
    {
      "instrument": 3,
      "note": 72,
      "startTick": 4752,
      "durationTicks": 47,
      "volume": 70
    },
    {
      "instrument": 5,
      "note": 60,
      "startTick": 4752,
      "durationTicks": 47,
      "volume": 72
    },
    {
      "instrument": 5,
      "note": 72,
      "startTick": 4752,
      "durationTicks": 47,
      "volume": 72
    },
    {
      "instrument": 1,
      "note": 46,
      "startTick": 4800,
      "durationTicks": 86,
      "volume": 64
    },
    {
      "instrument": 1,
      "note": 58,
      "startTick": 4800,
      "durationTicks": 95,
      "volume": 47
    },
    {
      "instrument": 3,
      "note": 62,
      "startTick": 4800,
      "durationTicks": 95,
      "volume": 70
    },
    {
      "instrument": 3,
      "note": 74,
      "startTick": 4800,
      "durationTicks": 95,
      "volume": 70
    },
    {
      "instrument": 4,
      "note": 34,
      "startTick": 4800,
      "durationTicks": 172,
      "volume": 62
    },
    {
      "instrument": 4,
      "note": 46,
      "startTick": 4800,
      "durationTicks": 172,
      "volume": 62
    },
    {
      "instrument": 4,
      "note": 58,
      "startTick": 4800,
      "durationTicks": 172,
      "volume": 62
    },
    {
      "instrument": 5,
      "note": 62,
      "startTick": 4800,
      "durationTicks": 95,
      "volume": 72
    },
    {
      "instrument": 5,
      "note": 74,
      "startTick": 4800,
      "durationTicks": 95,
      "volume": 72
    },
    {
      "instrument": 1,
      "note": 41,
      "startTick": 4896,
      "durationTicks": 86,
      "volume": 64
    },
    {
      "instrument": 1,
      "note": 53,
      "startTick": 4896,
      "durationTicks": 95,
      "volume": 47
    },
    {
      "instrument": 3,
      "note": 65,
      "startTick": 4896,
      "durationTicks": 95,
      "volume": 70
    },
    {
      "instrument": 3,
      "note": 77,
      "startTick": 4896,
      "durationTicks": 95,
      "volume": 70
    },
    {
      "instrument": 5,
      "note": 65,
      "startTick": 4896,
      "durationTicks": 95,
      "volume": 72
    },
    {
      "instrument": 5,
      "note": 77,
      "startTick": 4896,
      "durationTicks": 95,
      "volume": 72
    },
    {
      "instrument": 1,
      "note": 43,
      "startTick": 4992,
      "durationTicks": 86,
      "volume": 64
    },
    {
      "instrument": 1,
      "note": 55,
      "startTick": 4992,
      "durationTicks": 86,
      "volume": 64
    },
    {
      "instrument": 2,
      "note": 77,
      "startTick": 4992,
      "durationTicks": 23,
      "volume": 72
    },
    {
      "instrument": 4,
      "note": 43,
      "startTick": 4992,
      "durationTicks": 86,
      "volume": 62
    },
    {
      "instrument": 4,
      "note": 55,
      "startTick": 4992,
      "durationTicks": 86,
      "volume": 62
    },
    {
      "instrument": 2,
      "note": 75,
      "startTick": 5016,
      "durationTicks": 23,
      "volume": 72
    },
    {
      "instrument": 2,
      "note": 74,
      "startTick": 5040,
      "durationTicks": 47,
      "volume": 72
    },
    {
      "instrument": 3,
      "note": 65,
      "startTick": 5040,
      "durationTicks": 43,
      "volume": 62
    },
    {
      "instrument": 3,
      "note": 77,
      "startTick": 5040,
      "durationTicks": 43,
      "volume": 62
    },
    {
      "instrument": 5,
      "note": 65,
      "startTick": 5040,
      "durationTicks": 43,
      "volume": 64
    },
    {
      "instrument": 5,
      "note": 77,
      "startTick": 5040,
      "durationTicks": 43,
      "volume": 64
    },
    {
      "instrument": 1,
      "note": 46,
      "startTick": 5088,
      "durationTicks": 86,
      "volume": 64
    },
    {
      "instrument": 1,
      "note": 58,
      "startTick": 5088,
      "durationTicks": 86,
      "volume": 64
    },
    {
      "instrument": 3,
      "note": 68,
      "startTick": 5088,
      "durationTicks": 43,
      "volume": 62
    },
    {
      "instrument": 3,
      "note": 80,
      "startTick": 5088,
      "durationTicks": 43,
      "volume": 62
    },
    {
      "instrument": 4,
      "note": 46,
      "startTick": 5088,
      "durationTicks": 86,
      "volume": 62
    },
    {
      "instrument": 4,
      "note": 58,
      "startTick": 5088,
      "durationTicks": 86,
      "volume": 62
    },
    {
      "instrument": 5,
      "note": 65,
      "startTick": 5088,
      "durationTicks": 43,
      "volume": 64
    },
    {
      "instrument": 5,
      "note": 80,
      "startTick": 5088,
      "durationTicks": 43,
      "volume": 64
    },
    {
      "instrument": 3,
      "note": 65,
      "startTick": 5136,
      "durationTicks": 43,
      "volume": 62
    },
    {
      "instrument": 3,
      "note": 77,
      "startTick": 5136,
      "durationTicks": 43,
      "volume": 62
    },
    {
      "instrument": 5,
      "note": 65,
      "startTick": 5136,
      "durationTicks": 43,
      "volume": 64
    },
    {
      "instrument": 5,
      "note": 77,
      "startTick": 5136,
      "durationTicks": 43,
      "volume": 64
    },
    {
      "instrument": 1,
      "note": 55,
      "startTick": 5184,
      "durationTicks": 21,
      "volume": 64
    },
    {
      "instrument": 2,
      "note": 75,
      "startTick": 5184,
      "durationTicks": 86,
      "volume": 72
    },
    {
      "instrument": 3,
      "note": 60,
      "startTick": 5184,
      "durationTicks": 86,
      "volume": 62
    },
    {
      "instrument": 3,
      "note": 72,
      "startTick": 5184,
      "durationTicks": 86,
      "volume": 62
    },
    {
      "instrument": 3,
      "note": 75,
      "startTick": 5184,
      "durationTicks": 86,
      "volume": 62
    },
    {
      "instrument": 3,
      "note": 84,
      "startTick": 5184,
      "durationTicks": 86,
      "volume": 62
    },
    {
      "instrument": 4,
      "note": 48,
      "startTick": 5184,
      "durationTicks": 86,
      "volume": 62
    },
    {
      "instrument": 4,
      "note": 60,
      "startTick": 5184,
      "durationTicks": 86,
      "volume": 62
    },
    {
      "instrument": 5,
      "note": 60,
      "startTick": 5184,
      "durationTicks": 172,
      "volume": 64
    },
    {
      "instrument": 5,
      "note": 72,
      "startTick": 5184,
      "durationTicks": 172,
      "volume": 64
    },
    {
      "instrument": 5,
      "note": 84,
      "startTick": 5184,
      "durationTicks": 172,
      "volume": 64
    },
    {
      "instrument": 1,
      "note": 53,
      "startTick": 5208,
      "durationTicks": 21,
      "volume": 64
    },
    {
      "instrument": 1,
      "note": 51,
      "startTick": 5232,
      "durationTicks": 21,
      "volume": 64
    },
    {
      "instrument": 1,
      "note": 50,
      "startTick": 5256,
      "durationTicks": 21,
      "volume": 64
    },
    {
      "instrument": 1,
      "note": 48,
      "startTick": 5280,
      "durationTicks": 21,
      "volume": 64
    },
    {
      "instrument": 3,
      "note": 70,
      "startTick": 5280,
      "durationTicks": 86,
      "volume": 62
    },
    {
      "instrument": 3,
      "note": 82,
      "startTick": 5280,
      "durationTicks": 86,
      "volume": 62
    },
    {
      "instrument": 4,
      "note": 43,
      "startTick": 5280,
      "durationTicks": 86,
      "volume": 62
    },
    {
      "instrument": 4,
      "note": 55,
      "startTick": 5280,
      "durationTicks": 86,
      "volume": 62
    },
    {
      "instrument": 1,
      "note": 46,
      "startTick": 5304,
      "durationTicks": 21,
      "volume": 64
    },
    {
      "instrument": 1,
      "note": 44,
      "startTick": 5328,
      "durationTicks": 21,
      "volume": 64
    },
    {
      "instrument": 1,
      "note": 43,
      "startTick": 5352,
      "durationTicks": 21,
      "volume": 64
    },
    {
      "instrument": 1,
      "note": 44,
      "startTick": 5376,
      "durationTicks": 172,
      "volume": 64
    },
    {
      "instrument": 2,
      "note": 79,
      "startTick": 5376,
      "durationTicks": 21,
      "volume": 72
    },
    {
      "instrument": 3,
      "note": 68,
      "startTick": 5376,
      "durationTicks": 21,
      "volume": 62
    },
    {
      "instrument": 3,
      "note": 80,
      "startTick": 5376,
      "durationTicks": 21,
      "volume": 62
    },
    {
      "instrument": 4,
      "note": 44,
      "startTick": 5376,
      "durationTicks": 86,
      "volume": 62
    },
    {
      "instrument": 4,
      "note": 56,
      "startTick": 5376,
      "durationTicks": 86,
      "volume": 62
    },
    {
      "instrument": 0,
      "note": 72,
      "startTick": 5424,
      "durationTicks": 43,
      "volume": 72
    },
    {
      "instrument": 0,
      "note": 84,
      "startTick": 5424,
      "durationTicks": 43,
      "volume": 72
    },
    {
      "instrument": 2,
      "note": 79,
      "startTick": 5424,
      "durationTicks": 21,
      "volume": 72
    },
    {
      "instrument": 3,
      "note": 72,
      "startTick": 5424,
      "durationTicks": 43,
      "volume": 62
    },
    {
      "instrument": 3,
      "note": 84,
      "startTick": 5424,
      "durationTicks": 43,
      "volume": 62
    },
    {
      "instrument": 5,
      "note": 60,
      "startTick": 5424,
      "durationTicks": 21,
      "volume": 64
    },
    {
      "instrument": 5,
      "note": 72,
      "startTick": 5424,
      "durationTicks": 21,
      "volume": 64
    },
    {
      "instrument": 5,
      "note": 60,
      "startTick": 5448,
      "durationTicks": 21,
      "volume": 64
    },
    {
      "instrument": 5,
      "note": 72,
      "startTick": 5448,
      "durationTicks": 21,
      "volume": 64
    },
    {
      "instrument": 0,
      "note": 75,
      "startTick": 5472,
      "durationTicks": 43,
      "volume": 72
    },
    {
      "instrument": 0,
      "note": 87,
      "startTick": 5472,
      "durationTicks": 43,
      "volume": 72
    },
    {
      "instrument": 3,
      "note": 75,
      "startTick": 5472,
      "durationTicks": 43,
      "volume": 62
    },
    {
      "instrument": 3,
      "note": 87,
      "startTick": 5472,
      "durationTicks": 43,
      "volume": 62
    },
    {
      "instrument": 4,
      "note": 44,
      "startTick": 5472,
      "durationTicks": 86,
      "volume": 62
    },
    {
      "instrument": 4,
      "note": 56,
      "startTick": 5472,
      "durationTicks": 86,
      "volume": 62
    },
    {
      "instrument": 5,
      "note": 63,
      "startTick": 5472,
      "durationTicks": 43,
      "volume": 64
    },
    {
      "instrument": 5,
      "note": 75,
      "startTick": 5472,
      "durationTicks": 43,
      "volume": 64
    },
    {
      "instrument": 2,
      "note": 79,
      "startTick": 5496,
      "durationTicks": 21,
      "volume": 72
    },
    {
      "instrument": 0,
      "note": 72,
      "startTick": 5520,
      "durationTicks": 43,
      "volume": 72
    },
    {
      "instrument": 0,
      "note": 84,
      "startTick": 5520,
      "durationTicks": 43,
      "volume": 72
    },
    {
      "instrument": 3,
      "note": 72,
      "startTick": 5520,
      "durationTicks": 43,
      "volume": 62
    },
    {
      "instrument": 3,
      "note": 84,
      "startTick": 5520,
      "durationTicks": 43,
      "volume": 62
    },
    {
      "instrument": 5,
      "note": 60,
      "startTick": 5520,
      "durationTicks": 43,
      "volume": 64
    },
    {
      "instrument": 5,
      "note": 72,
      "startTick": 5520,
      "durationTicks": 43,
      "volume": 64
    },
    {
      "instrument": 0,
      "note": 79,
      "startTick": 5568,
      "durationTicks": 86,
      "volume": 72
    },
    {
      "instrument": 2,
      "note": 79,
      "startTick": 5568,
      "durationTicks": 21,
      "volume": 72
    },
    {
      "instrument": 3,
      "note": 79,
      "startTick": 5568,
      "durationTicks": 86,
      "volume": 62
    },
    {
      "instrument": 3,
      "note": 91,
      "startTick": 5568,
      "durationTicks": 86,
      "volume": 62
    },
    {
      "instrument": 4,
      "note": 44,
      "startTick": 5568,
      "durationTicks": 86,
      "volume": 62
    },
    {
      "instrument": 4,
      "note": 56,
      "startTick": 5568,
      "durationTicks": 86,
      "volume": 62
    },
    {
      "instrument": 5,
      "note": 67,
      "startTick": 5568,
      "durationTicks": 86,
      "volume": 64
    },
    {
      "instrument": 5,
      "note": 79,
      "startTick": 5568,
      "durationTicks": 86,
      "volume": 64
    },
    {
      "instrument": 2,
      "note": 79,
      "startTick": 5616,
      "durationTicks": 21,
      "volume": 72
    },
    {
      "instrument": 0,
      "note": 75,
      "startTick": 5664,
      "durationTicks": 86,
      "volume": 72
    },
    {
      "instrument": 0,
      "note": 87,
      "startTick": 5664,
      "durationTicks": 86,
      "volume": 72
    },
    {
      "instrument": 3,
      "note": 75,
      "startTick": 5664,
      "durationTicks": 86,
      "volume": 62
    },
    {
      "instrument": 3,
      "note": 87,
      "startTick": 5664,
      "durationTicks": 86,
      "volume": 62
    },
    {
      "instrument": 4,
      "note": 44,
      "startTick": 5664,
      "durationTicks": 86,
      "volume": 62
    },
    {
      "instrument": 4,
      "note": 56,
      "startTick": 5664,
      "durationTicks": 86,
      "volume": 62
    },
    {
      "instrument": 5,
      "note": 63,
      "startTick": 5664,
      "durationTicks": 86,
      "volume": 64
    },
    {
      "instrument": 5,
      "note": 75,
      "startTick": 5664,
      "durationTicks": 86,
      "volume": 64
    },
    {
      "instrument": 2,
      "note": 79,
      "startTick": 5688,
      "durationTicks": 21,
      "volume": 72
    },
    {
      "instrument": 0,
      "note": 58,
      "startTick": 5760,
      "durationTicks": 345,
      "volume": 72
    },
    {
      "instrument": 0,
      "note": 74,
      "startTick": 5760,
      "durationTicks": 345,
      "volume": 72
    },
    {
      "instrument": 0,
      "note": 77,
      "startTick": 5760,
      "durationTicks": 345,
      "volume": 72
    },
    {
      "instrument": 1,
      "note": 46,
      "startTick": 5760,
      "durationTicks": 172,
      "volume": 64
    },
    {
      "instrument": 2,
      "note": 77,
      "startTick": 5760,
      "durationTicks": 21,
      "volume": 72
    },
    {
      "instrument": 3,
      "note": 65,
      "startTick": 5760,
      "durationTicks": 172,
      "volume": 62
    },
    {
      "instrument": 3,
      "note": 77,
      "startTick": 5760,
      "durationTicks": 172,
      "volume": 62
    },
    {
      "instrument": 4,
      "note": 46,
      "startTick": 5760,
      "durationTicks": 86,
      "volume": 62
    },
    {
      "instrument": 4,
      "note": 50,
      "startTick": 5760,
      "durationTicks": 172,
      "volume": 62
    },
    {
      "instrument": 4,
      "note": 53,
      "startTick": 5760,
      "durationTicks": 172,
      "volume": 62
    },
    {
      "instrument": 4,
      "note": 58,
      "startTick": 5760,
      "durationTicks": 345,
      "volume": 62
    },
    {
      "instrument": 5,
      "note": 65,
      "startTick": 5760,
      "durationTicks": 345,
      "volume": 64
    },
    {
      "instrument": 5,
      "note": 77,
      "startTick": 5760,
      "durationTicks": 345,
      "volume": 64
    },
    {
      "instrument": 2,
      "note": 77,
      "startTick": 5808,
      "durationTicks": 21,
      "volume": 72
    },
    {
      "instrument": 1,
      "note": 41,
      "startTick": 5856,
      "durationTicks": 86,
      "volume": 64
    },
    {
      "instrument": 4,
      "note": 46,
      "startTick": 5856,
      "durationTicks": 86,
      "volume": 62
    },
    {
      "instrument": 4,
      "note": 50,
      "startTick": 5928,
      "durationTicks": 172,
      "volume": 62
    },
    {
      "instrument": 4,
      "note": 53,
      "startTick": 5928,
      "durationTicks": 172,
      "volume": 62
    },
    {
      "instrument": 1,
      "note": 46,
      "startTick": 5952,
      "durationTicks": 86,
      "volume": 64
    },
    {
      "instrument": 2,
      "note": 70,
      "startTick": 5952,
      "durationTicks": 21,
      "volume": 72
    },
    {
      "instrument": 4,
      "note": 46,
      "startTick": 5952,
      "durationTicks": 86,
      "volume": 62
    },
    {
      "instrument": 5,
      "note": 65,
      "startTick": 5952,
      "durationTicks": 172,
      "volume": 64
    },
    {
      "instrument": 5,
      "note": 77,
      "startTick": 5952,
      "durationTicks": 172,
      "volume": 64
    },
    {
      "instrument": 1,
      "note": 46,
      "startTick": 6048,
      "durationTicks": 86,
      "volume": 64
    },
    {
      "instrument": 2,
      "note": 70,
      "startTick": 6048,
      "durationTicks": 21,
      "volume": 72
    },
    {
      "instrument": 3,
      "note": 82,
      "startTick": 6048,
      "durationTicks": 21,
      "volume": 62
    },
    {
      "instrument": 4,
      "note": 46,
      "startTick": 6048,
      "durationTicks": 86,
      "volume": 62
    },
    {
      "instrument": 2,
      "note": 69,
      "startTick": 6072,
      "durationTicks": 21,
      "volume": 72
    },
    {
      "instrument": 1,
      "note": 47,
      "startTick": 6096,
      "durationTicks": 43,
      "volume": 64
    },
    {
      "instrument": 2,
      "note": 70,
      "startTick": 6096,
      "durationTicks": 21,
      "volume": 72
    },
    {
      "instrument": 3,
      "note": 83,
      "startTick": 6096,
      "durationTicks": 21,
      "volume": 62
    },
    {
      "instrument": 2,
      "note": 71,
      "startTick": 6120,
      "durationTicks": 21,
      "volume": 72
    },
    {
      "instrument": 0,
      "note": 60,
      "startTick": 6144,
      "durationTicks": 23,
      "volume": 64
    },
    {
      "instrument": 0,
      "note": 72,
      "startTick": 6144,
      "durationTicks": 23,
      "volume": 64
    },
    {
      "instrument": 0,
      "note": 84,
      "startTick": 6144,
      "durationTicks": 23,
      "volume": 64
    },
    {
      "instrument": 1,
      "note": 36,
      "startTick": 6144,
      "durationTicks": 23,
      "volume": 64
    },
    {
      "instrument": 1,
      "note": 48,
      "startTick": 6144,
      "durationTicks": 23,
      "volume": 64
    },
    {
      "instrument": 2,
      "note": 72,
      "startTick": 6144,
      "durationTicks": 23,
      "volume": 72
    },
    {
      "instrument": 3,
      "note": 60,
      "startTick": 6144,
      "durationTicks": 23,
      "volume": 64
    },
    {
      "instrument": 3,
      "note": 84,
      "startTick": 6144,
      "durationTicks": 23,
      "volume": 64
    },
    {
      "instrument": 6,
      "note": 60,
      "startTick": 6144,
      "durationTicks": 95,
      "volume": 64
    },
    {
      "instrument": 6,
      "note": 72,
      "startTick": 6144,
      "durationTicks": 95,
      "volume": 64
    },
    {
      "instrument": 6,
      "note": 84,
      "startTick": 6144,
      "durationTicks": 95,
      "volume": 64
    },
    {
      "instrument": 7,
      "note": 36,
      "startTick": 6144,
      "durationTicks": 95,
      "volume": 64
    },
    {
      "instrument": 7,
      "note": 48,
      "startTick": 6144,
      "durationTicks": 95,
      "volume": 64
    },
    {
      "instrument": 7,
      "note": 60,
      "startTick": 6144,
      "durationTicks": 95,
      "volume": 64
    },
    {
      "instrument": 7,
      "note": 72,
      "startTick": 6144,
      "durationTicks": 95,
      "volume": 64
    },
    {
      "instrument": 7,
      "note": 84,
      "startTick": 6144,
      "durationTicks": 95,
      "volume": 64
    }
  ]
}
